[
  {
    "id": "JEE_Main_2015_1xgTTVc3tihLuKOr",
    "exam": "JEE Main",
    "year": 2015,
    "shift": "jee-main-2015-offline",
    "subject": "Chemistry",
    "topic": "Solutions",
    "micro_topic": "Relative Lowering Of Vapour Pressure And Roults Law",
    "question_text": "The vapour pressure of acetone at 20oC is 185 torr. When 1.2 g of a non-volatile substance was dissolved in\n100 g of acetone at 20oC, its vapour pressure was 183 torr. The molar mass (g mol-1) of the substance is:",
    "question_type": "MCQ_single",
    "difficulty": 3,
    "concepts_tested": [],
    "answer": "A",
    "marks": 4
  },
  {
    "id": "JEE_Main_2015_RR1LJVrcIoDjJ04y",
    "exam": "JEE Main",
    "year": 2015,
    "shift": "jee-main-2015-offline",
    "subject": "Chemistry",
    "topic": "Basics Of Organic Chemistry",
    "micro_topic": "Isomerism",
    "question_text": "Which of the following compounds will exhibit geometrical isomerism?",
    "question_type": "MCQ_single",
    "difficulty": 3,
    "concepts_tested": [],
    "answer": "D",
    "marks": 4
  },
  {
    "id": "JEE_Main_2015_8aPlaiwmP4fkNkrG",
    "exam": "JEE Main",
    "year": 2015,
    "shift": "jee-main-2015-offline",
    "subject": "Chemistry",
    "topic": "Basics Of Organic Chemistry",
    "micro_topic": "Purification Of Organic Compounds",
    "question_text": "In Carius method of estimation of halogens, 250 mg of an organic compound gave 141 mg of AgBr. The\npercentage of bromine in the compound is: (at. Mass Ag = 108; Br = 80)",
    "question_type": "MCQ_single",
    "difficulty": 3,
    "concepts_tested": [],
    "answer": "D",
    "marks": 4
  },
  {
    "id": "JEE_Main_2015_slcAxWaeZqwRmZga",
    "exam": "JEE Main",
    "year": 2015,
    "shift": "jee-main-2015-offline",
    "subject": "Chemistry",
    "topic": "Chemical Equilibrium",
    "micro_topic": "Chemical Equilibrium Law Of Mass Action And Equilibrium Constant",
    "question_text": "The standard Gibbs energy change at 300 K for the reaction 2A $$\\leftrightharpoons$$ B + C is 2494.2 J. At a given time,\nthe composition of the reaction mixture is [A] = 1/2, [B] = 2 and [C] = 1/2. The reaction proceeds in the: [R = 8.314 J/K/mol, e = 2.718]",
    "question_type": "MCQ_single",
    "difficulty": 3,
    "concepts_tested": [],
    "answer": "A",
    "marks": 4
  },
  {
    "id": "JEE_Main_2015_abw0HPkOJTHzb9O6",
    "exam": "JEE Main",
    "year": 2015,
    "shift": "jee-main-2015-offline",
    "subject": "Chemistry",
    "topic": "Thermodynamics",
    "micro_topic": "Entropy Free Energy Change And Spontaneity",
    "question_text": "The following reaction is performed at 298 K\n2NO(g) +  O2 (g) $$\\leftrightharpoons$$ 2NO2 (g) \nThe standard free energy of formation of NO(g) is 86.6 kJ/mol at 298 K. What is the standard free energy\nof formation of NO2(g) at 298 K? (KP = 1.6 × 1012)",
    "question_type": "MCQ_single",
    "difficulty": 3,
    "concepts_tested": [],
    "answer": "C",
    "marks": 4
  },
  {
    "id": "JEE_Main_2015_uFDqfbIrxOPsFFmR",
    "exam": "JEE Main",
    "year": 2015,
    "shift": "jee-main-2015-offline",
    "subject": "Chemistry",
    "topic": "Some Basic Concepts Of Chemistry",
    "micro_topic": "Mole Concept",
    "question_text": "The molecular formula of a commercial resin used for exchanging ions in water softening is\nC8H7SO3Na (Mol. Wt. 206). What would be the maximum uptake of Ca2+ ions by the resin when expressed in mole per gram resin?",
    "question_type": "MCQ_single",
    "difficulty": 3,
    "concepts_tested": [],
    "answer": "B",
    "marks": 4
  },
  {
    "id": "JEE_Main_2015_wQZhoL2I8GFK6YPP",
    "exam": "JEE Main",
    "year": 2015,
    "shift": "jee-main-2015-offline",
    "subject": "Chemistry",
    "topic": "Electrochemistry",
    "micro_topic": "Conductance And Electrolysis",
    "question_text": "Two Faraday of electricity is passed through a solution of CuSO4. The mass of copper deposited at the\ncathode is: (at. mass of Cu = 63.5 amu)",
    "question_type": "MCQ_single",
    "difficulty": 3,
    "concepts_tested": [],
    "answer": "A",
    "marks": 4
  },
  {
    "id": "JEE_Main_2015_InA3umoGpofamZ2t",
    "exam": "JEE Main",
    "year": 2015,
    "shift": "jee-main-2015-offline",
    "subject": "Chemistry",
    "topic": "Chemical Bonding And Molecular Structure",
    "micro_topic": "Hydrogen Bonding",
    "question_text": "The intermolecular interaction that is dependent on the inverse cube of distance between the molecule is:",
    "question_type": "MCQ_single",
    "difficulty": 3,
    "concepts_tested": [],
    "answer": "C",
    "marks": 4
  },
  {
    "id": "JEE_Main_2015_fjeiTMJaUvnjveA4",
    "exam": "JEE Main",
    "year": 2015,
    "shift": "jee-main-2015-offline",
    "subject": "Chemistry",
    "topic": "Aldehydes Ketones And Carboxylic Acids",
    "micro_topic": "Preparation Methods For Both Aldehydes And Ketones",
    "question_text": "Which compound would give $$5$$ - keto - $$2$$ - methylhexanal upon ozonolysis?",
    "question_type": "MCQ_single",
    "difficulty": 3,
    "concepts_tested": [],
    "answer": "D",
    "marks": 4
  },
  {
    "id": "JEE_Main_2015_odtPpygnB816JhsZ",
    "exam": "JEE Main",
    "year": 2015,
    "shift": "jee-main-2015-offline",
    "subject": "Chemistry",
    "topic": "Compounds Containing Nitrogen",
    "micro_topic": "Diazonium Salts And Other Nitrogen Containing Compounds",
    "question_text": "In the reaction \n\nThe product $$E$$ is :",
    "question_type": "MCQ_single",
    "difficulty": 3,
    "concepts_tested": [],
    "answer": "A",
    "marks": 4
  },
  {
    "id": "JEE_Main_2015_xkWSCELBONRsag68",
    "exam": "JEE Main",
    "year": 2015,
    "shift": "jee-main-2015-offline",
    "subject": "Chemistry",
    "topic": "D And F Block Elements",
    "micro_topic": "Properties Of Transition Elements",
    "question_text": "Match the catalysts to the correct processes :\n\n.tg  {border-collapse:collapse;border-spacing:0;border:none;border-color:#999;}\n.tg td{font-family:Arial, sans-serif;font-size:14px;padding:10px 5px;border-style:solid;border-width:0px;overflow:hidden;word-break:normal;border-color:#999;color:#444;background-color:#F7FDFA;}\n.tg th{font-family:Arial, sans-serif;font-size:14px;font-weight:normal;padding:10px 5px;border-style:solid;border-width:0px;overflow:hidden;word-break:normal;border-color:#999;color:#fff;background-color:#26ADE4;}\n.tg .tg-p7ly{font-weight:bold;font-size:20px;text-align:center}\n.tg .tg-4kyz{font-size:20px;text-align:center}\n\n\n  \n    \n    Catalyst\n    \n    Process\n  \n  \n    (A)\n    TiCl3\n    (i)\n    Wacker process\n  \n  \n    (B)\n    PdCl2\n    (ii)\n    Ziegler - Nattapolymerization\n  \n  \n    (C)\n    CuCl2\n    (iii)\n    Contact process\n  \n  \n    (D)\n    V2O5\n    (iv)\n    Deacon's process",
    "question_type": "MCQ_single",
    "difficulty": 3,
    "concepts_tested": [],
    "answer": "D",
    "marks": 4
  },
  {
    "id": "JEE_Main_2015_tt65GxVDHU4gGy2D",
    "exam": "JEE Main",
    "year": 2015,
    "shift": "jee-main-2015-offline",
    "subject": "Chemistry",
    "topic": "Biomolecules",
    "micro_topic": "Vitamins And Nucleic Acids",
    "question_text": "Which of the vitamins given below is water soluble?",
    "question_type": "MCQ_single",
    "difficulty": 3,
    "concepts_tested": [],
    "answer": "D",
    "marks": 4
  },
  {
    "id": "JEE_Main_2015_7dmKpmZoRmckHRGv",
    "exam": "JEE Main",
    "year": 2015,
    "shift": "jee-main-2015-offline",
    "subject": "Chemistry",
    "topic": "Haloalkanes And Haloarenes",
    "micro_topic": "Haloalkanes",
    "question_text": "The synthesis of alkyl fluorides is best accomplished by:",
    "question_type": "MCQ_single",
    "difficulty": 3,
    "concepts_tested": [],
    "answer": "C",
    "marks": 4
  },
  {
    "id": "JEE_Main_2015_eMllOmkYpMeILw7S",
    "exam": "JEE Main",
    "year": 2015,
    "shift": "jee-main-2015-offline",
    "subject": "Chemistry",
    "topic": "D And F Block Elements",
    "micro_topic": "Important Compounds Of Transition Elements",
    "question_text": "The colour of KMnO4 is due to :",
    "question_type": "MCQ_single",
    "difficulty": 3,
    "concepts_tested": [],
    "answer": "B",
    "marks": 4
  },
  {
    "id": "JEE_Main_2015_GOE59X09V0KkqsAX",
    "exam": "JEE Main",
    "year": 2015,
    "shift": "jee-main-2015-offline",
    "subject": "Chemistry",
    "topic": "Aldehydes Ketones And Carboxylic Acids",
    "micro_topic": "Method Of Preparation For Aldehydes",
    "question_text": "In the following sequence of reactions:\n\nThe product C is",
    "question_type": "MCQ_single",
    "difficulty": 3,
    "concepts_tested": [],
    "answer": "C",
    "marks": 4
  },
  {
    "id": "JEE_Main_2015_SgYdXDfyjDlA5dSk",
    "exam": "JEE Main",
    "year": 2015,
    "shift": "jee-main-2015-offline",
    "subject": "Chemistry",
    "topic": "Coordination Compounds",
    "micro_topic": "Isomerism Of Coordination Compounds",
    "question_text": "The number of geometric isomers that can exist for square planar [Pt (Cl) (py) (NH3) (NH2OH)]+ is (py = pyridine) :",
    "question_type": "MCQ_single",
    "difficulty": 3,
    "concepts_tested": [],
    "answer": "A",
    "marks": 4
  },
  {
    "id": "JEE_Main_2015_svPpDst4r3r0aDg5",
    "exam": "JEE Main",
    "year": 2015,
    "shift": "jee-main-2015-offline",
    "subject": "Chemistry",
    "topic": "Coordination Compounds",
    "micro_topic": "Crystal Field Theory Cft",
    "question_text": "Which of the following compounds is not colored yellow?",
    "question_type": "MCQ_single",
    "difficulty": 3,
    "concepts_tested": [],
    "answer": "D",
    "marks": 4
  },
  {
    "id": "JEE_Main_2015_tGD5YikwpgBoGz2p",
    "exam": "JEE Main",
    "year": 2015,
    "shift": "jee-main-2015-offline",
    "subject": "Chemistry",
    "topic": "Chemical Kinetics And Nuclear Chemistry",
    "micro_topic": "Integrated Rate Law Equations",
    "question_text": "Higher order (>3) reactions are rare due to",
    "question_type": "MCQ_single",
    "difficulty": 3,
    "concepts_tested": [],
    "answer": "D",
    "marks": 4
  },
  {
    "id": "JEE_Main_2015_Fkyt13wViFAxUzyK",
    "exam": "JEE Main",
    "year": 2015,
    "shift": "jee-main-2015-offline",
    "subject": "Chemistry",
    "topic": "P Block Elements",
    "micro_topic": "Group 16 Elements Oxygen Family",
    "question_text": "Assertion : Nitrogen and Oxygen are the main components in the atmosphere but these do not react to\nform oxides of nitrogen.\nReason : The reaction between nitrogen and oxygen requires high temperature.",
    "question_type": "MCQ_single",
    "difficulty": 3,
    "concepts_tested": [],
    "answer": "A",
    "marks": 4
  },
  {
    "id": "JEE_Main_2015_Ut5uj1dVpqLXtlWr",
    "exam": "JEE Main",
    "year": 2015,
    "shift": "jee-main-2015-offline",
    "subject": "Chemistry",
    "topic": "P Block Elements",
    "micro_topic": "Group 18 Elements Inert Or Noble Gases",
    "question_text": "Which one has the highest boiling point?",
    "question_type": "MCQ_single",
    "difficulty": 3,
    "concepts_tested": [],
    "answer": "C",
    "marks": 4
  },
  {
    "id": "JEE_Main_2015_mon03lcV7SBvYiyy",
    "exam": "JEE Main",
    "year": 2015,
    "shift": "jee-main-2015-offline",
    "subject": "Chemistry",
    "topic": "Periodic Table And Periodicity",
    "micro_topic": "Atomic And Ionic Radius",
    "question_text": "The ionic radii (in Å) of N3–, O2– and F– are respectively:",
    "question_type": "MCQ_single",
    "difficulty": 3,
    "concepts_tested": [],
    "answer": "B",
    "marks": 4
  },
  {
    "id": "JEE_Main_2015_vIlUiuau2OiTPDR4",
    "exam": "JEE Main",
    "year": 2015,
    "shift": "jee-main-2015-offline",
    "subject": "Chemistry",
    "topic": "Structure Of Atom",
    "micro_topic": "Bohrs Model For Hydrogen Atom",
    "question_text": "Which of the following is the energy of a possible excited state of hydrogen?",
    "question_type": "MCQ_single",
    "difficulty": 3,
    "concepts_tested": [],
    "answer": "B",
    "marks": 4
  },
  {
    "id": "JEE_Main_2015_RtZ9MK0tEqbtwJlp",
    "exam": "JEE Main",
    "year": 2015,
    "shift": "jee-main-2015-offline",
    "subject": "Mathematics",
    "topic": "Limits Continuity And Differentiability",
    "micro_topic": "Differentiability",
    "question_text": "If the function.\n$$g\\left( x \\right) = \\left\\{ {\\matrix{\n   {k\\sqrt {x + 1} ,} & {0 \\le x \\le 3}  \\cr \n   {m\\,x + 2,} & {3 < x \\le 5}  \\cr \n\n } } \\right.$$\nis differentiable, then the value of $$k+m$$ is :",
    "question_type": "MCQ_single",
    "difficulty": 3,
    "concepts_tested": [],
    "answer": "C",
    "marks": 4
  },
  {
    "id": "JEE_Main_2015_lB1b64UMGJQfxOW0",
    "exam": "JEE Main",
    "year": 2015,
    "shift": "jee-main-2015-offline",
    "subject": "Mathematics",
    "topic": "Statistics",
    "micro_topic": "Calculation Of Mean Median And Mode Of Grouped And Ungrouped Data",
    "question_text": "The mean of the data set comprising of 16 observations is 16. If one of the observation valued 16 is deleted\nand three new observations valued 3, 4 and 5 are added to the data, then the mean of the resultant data, is :",
    "question_type": "MCQ_single",
    "difficulty": 3,
    "concepts_tested": [],
    "answer": "B",
    "marks": 4
  },
  {
    "id": "JEE_Main_2015_R1Gk6O2WAxXViPUh",
    "exam": "JEE Main",
    "year": 2015,
    "shift": "jee-main-2015-offline",
    "subject": "Mathematics",
    "topic": "Limits Continuity And Differentiability",
    "micro_topic": "Limits Of Trigonometric Functions",
    "question_text": "$$\\mathop {\\lim }\\limits_{x \\to 0} {{\\left( {1 - \\cos 2x} \\right)\\left( {3 + \\cos x} \\right)} \\over {x\\tan 4x}}$$ is equal to",
    "question_type": "MCQ_single",
    "difficulty": 3,
    "concepts_tested": [],
    "answer": "A",
    "marks": 4
  },
  {
    "id": "JEE_Main_2015_RL48R3LIbXTYoq2f",
    "exam": "JEE Main",
    "year": 2015,
    "shift": "jee-main-2015-offline",
    "subject": "Mathematics",
    "topic": "Quadratic Equation And Inequalities",
    "micro_topic": "Relation Between Roots And Coefficients",
    "question_text": "Let $$\\alpha $$ and $$\\beta $$ be the roots of equation $${x^2} - 6x - 2 = 0$$. If $${a_n} = {\\alpha ^n} - {\\beta ^n},$$  for $$n \\ge 1,$$ then the value of $${{{a_{10}} - 2{a_8}} \\over {2{a_9}}}$$  is equal to :",
    "question_type": "MCQ_single",
    "difficulty": 3,
    "concepts_tested": [],
    "answer": "A",
    "marks": 4
  },
  {
    "id": "JEE_Main_2015_v0MDihlczrEKxer8",
    "exam": "JEE Main",
    "year": 2015,
    "shift": "jee-main-2015-offline",
    "subject": "Mathematics",
    "topic": "Probability",
    "micro_topic": "Permutation And Combination Based Problem",
    "question_text": "If $$12$$ different balls are to be placed in $$3$$ identical boxes, then the probability that one of the boxes contains exactly $$3$$ balls is :",
    "question_type": "MCQ_single",
    "difficulty": 3,
    "concepts_tested": [],
    "answer": "C",
    "marks": 4
  },
  {
    "id": "JEE_Main_2015_t8g0J8Q5j5Uqh3wN",
    "exam": "JEE Main",
    "year": 2015,
    "shift": "jee-main-2015-offline",
    "subject": "Mathematics",
    "topic": "Definite Integration",
    "micro_topic": "Properties Of Definite Integration",
    "question_text": "The integral \n$$\\int\\limits_2^4 {{{\\log \\,{x^2}} \\over {\\log {x^2} + \\log \\left( {36 - 12x + {x^2}} \\right)}}dx} $$   is equal to :",
    "question_type": "MCQ_single",
    "difficulty": 3,
    "concepts_tested": [],
    "answer": "A",
    "marks": 4
  },
  {
    "id": "JEE_Main_2015_3IxYLRiMUbRQ20y2",
    "exam": "JEE Main",
    "year": 2015,
    "shift": "jee-main-2015-offline",
    "subject": "Mathematics",
    "topic": "Differential Equations",
    "micro_topic": "Linear Differential Equations",
    "question_text": "Let $$y(x)$$ be the solution of the differential equation \n$$\\left( {x\\,\\log x} \\right){{dy} \\over {dx}} + y = 2x\\,\\log x,\\left( {x \\ge 1} \\right).$$ Then $$y(e)$$ is equal to :",
    "question_type": "MCQ_single",
    "difficulty": 3,
    "concepts_tested": [],
    "answer": "A",
    "marks": 4
  },
  {
    "id": "JEE_Main_2015_XTxcDJGWpMyOANNI",
    "exam": "JEE Main",
    "year": 2015,
    "shift": "jee-main-2015-offline",
    "subject": "Mathematics",
    "topic": "Area Under The Curves",
    "micro_topic": "Area Bounded Between The Curves",
    "question_text": "The area (in sq. units) of the region described by \n$$\\left\\{ {\\left( {x,y} \\right):{y^2} \\le 2x} \\right.$$ and $$\\left. {y \\ge 4x - 1} \\right\\}$$ is :",
    "question_type": "MCQ_single",
    "difficulty": 3,
    "concepts_tested": [],
    "answer": "B",
    "marks": 4
  },
  {
    "id": "JEE_Main_2015_nZ3cEdvpgAwa9myY",
    "exam": "JEE Main",
    "year": 2015,
    "shift": "jee-main-2015-offline",
    "subject": "Mathematics",
    "topic": "Indefinite Integrals",
    "micro_topic": "Integration By Substitution",
    "question_text": "The integral $$\\int {{{dx} \\over {{x^2}{{\\left( {{x^4} + 1} \\right)}^{3/4}}}}} $$ equals :",
    "question_type": "MCQ_single",
    "difficulty": 3,
    "concepts_tested": [],
    "answer": "B",
    "marks": 4
  },
  {
    "id": "JEE_Main_2015_brxKL055e9VwbMXT",
    "exam": "JEE Main",
    "year": 2015,
    "shift": "jee-main-2015-offline",
    "subject": "Mathematics",
    "topic": "Matrices And Determinants",
    "micro_topic": "Solutions Of System Of Linear Equations In Two Or Three Variables Using Determinants And Matrices",
    "question_text": "The set of all values of $$\\lambda $$ for which the system of linear equations:\n$$\\matrix{\n   {2{x_1} - 2{x_2} + {x_3} = \\lambda {x_1}}  \\cr \n   {2{x_1} - 3{x_2} + 2{x_3} = \\lambda {x_2}}  \\cr \n   { - {x_1} + 2{x_2} = \\lambda {x_3}}  \\cr \n\n } $$\nhas a non-trivial solution",
    "question_type": "MCQ_single",
    "difficulty": 3,
    "concepts_tested": [],
    "answer": "A",
    "marks": 4
  },
  {
    "id": "JEE_Main_2015_JAEcF3gxW0HGEZRy",
    "exam": "JEE Main",
    "year": 2015,
    "shift": "jee-main-2015-offline",
    "subject": "Mathematics",
    "topic": "Application Of Derivatives",
    "micro_topic": "Maxima And Minima",
    "question_text": "Let $$f(x)$$ be a polynomial of degree four having extreme values \nat $$x=1$$ and $$x=2$$. If $$\\mathop {\\lim }\\limits_{x \\to 0} \\left[ {1 + {{f\\left( x \\right)} \\over {{x^2}}}} \\right] = 3$$, then f$$(2)$$ is equal to :",
    "question_type": "MCQ_single",
    "difficulty": 3,
    "concepts_tested": [],
    "answer": "A",
    "marks": 4
  },
  {
    "id": "JEE_Main_2015_amsDpowk5keRB2xC",
    "exam": "JEE Main",
    "year": 2015,
    "shift": "jee-main-2015-offline",
    "subject": "Mathematics",
    "topic": "Matrices And Determinants",
    "micro_topic": "Transpose Of A Matrix",
    "question_text": "If $$A = \\left[ {\\matrix{\n   1 & 2 & 2  \\cr \n   2 & 1 & { - 2}  \\cr \n   a & 2 & b  \\cr \n\n } } \\right]$$ is a matrix satisfying the equation \n$$A{A^T} = 9\\text{I},$$ where $$I$$ is $$3 \\times 3$$ identity matrix, then the ordered \npair $$(a, b)$$ is equal to :",
    "question_type": "MCQ_single",
    "difficulty": 3,
    "concepts_tested": [],
    "answer": "B",
    "marks": 4
  },
  {
    "id": "JEE_Main_2015_tb7Srq7xtkaCBPWe",
    "exam": "JEE Main",
    "year": 2015,
    "shift": "jee-main-2015-offline",
    "subject": "Mathematics",
    "topic": "Inverse Trigonometric Functions",
    "micro_topic": "Properties Of Inverse Trigonometric Functions",
    "question_text": "Let $${\\tan ^{ - 1}}y = {\\tan ^{ - 1}}x + {\\tan ^{ - 1}}\\left( {{{2x} \\over {1 - {x^2}}}} \\right),$$ \n where $$\\left| x \\right| < {1 \\over {\\sqrt 3 }}.$$ Then a value of $$y$$ is :",
    "question_type": "MCQ_single",
    "difficulty": 3,
    "concepts_tested": [],
    "answer": "C",
    "marks": 4
  },
  {
    "id": "JEE_Main_2015_2KV25TyV87muR2Xt",
    "exam": "JEE Main",
    "year": 2015,
    "shift": "jee-main-2015-offline",
    "subject": "Mathematics",
    "topic": "Parabola",
    "micro_topic": "Locus",
    "question_text": "Let $$O$$ be the vertex and $$Q$$ be any point on the parabola, $${{x^2} = 8y}$$. If the point $$P$$ divides the line segment $$OQ$$ internally in the ratio $$1:3$$, then locus of $$P$$ is :",
    "question_type": "MCQ_single",
    "difficulty": 3,
    "concepts_tested": [],
    "answer": "B",
    "marks": 4
  },
  {
    "id": "JEE_Main_2015_53q58LReyCXabFV0",
    "exam": "JEE Main",
    "year": 2015,
    "shift": "jee-main-2015-offline",
    "subject": "Mathematics",
    "topic": "Circle",
    "micro_topic": "Basic Theorems Of A Circle",
    "question_text": "Locus of the image of the point $$(2, 3)$$ in the line $$\\left( {2x - 3y + 4} \\right) + k\\left( {x - 2y + 3} \\right) = 0,\\,k \\in R,$$  is a :",
    "question_type": "MCQ_single",
    "difficulty": 3,
    "concepts_tested": [],
    "answer": "A",
    "marks": 4
  },
  {
    "id": "JEE_Main_2015_Cr16jGUNappIEabn",
    "exam": "JEE Main",
    "year": 2015,
    "shift": "jee-main-2015-offline",
    "subject": "Mathematics",
    "topic": "Straight Lines And Pair Of Straight Lines",
    "micro_topic": "Area Of Triangle And Condition Of Collinearity",
    "question_text": "The number of points, having both co-ordinates as integers, that lie in the interior of the triangle with vertices $$(0, 0)$$  $$(0, 41)$$ and $$(41, 0)$$ is :",
    "question_type": "MCQ_single",
    "difficulty": 3,
    "concepts_tested": [],
    "answer": "B",
    "marks": 4
  },
  {
    "id": "JEE_Main_2015_YBEbaVOfFKiWxDON",
    "exam": "JEE Main",
    "year": 2015,
    "shift": "jee-main-2015-offline",
    "subject": "Mathematics",
    "topic": "Sequences And Series",
    "micro_topic": "Am Gm And Hm",
    "question_text": "If m is the A.M. of two distinct real numbers l and n $$(l,n > 1)$$ and $${G_1},{G_2}$$ and $${G_3}$$ are three geometric means between $$l$$ and n, then $$G_1^4\\, + 2G_2^4\\, + G_3^4$$ equals:",
    "question_type": "MCQ_single",
    "difficulty": 3,
    "concepts_tested": [],
    "answer": "D",
    "marks": 4
  },
  {
    "id": "JEE_Main_2015_cpWdidtToPeRE0b1",
    "exam": "JEE Main",
    "year": 2015,
    "shift": "jee-main-2015-offline",
    "subject": "Mathematics",
    "topic": "Permutations And Combinations",
    "micro_topic": "Number Of Permutations",
    "question_text": "The number of integers greater than 6,000 that can be formed, using the digits 3, 5, 6, 7 and 8, without repetition, is:",
    "question_type": "MCQ_single",
    "difficulty": 3,
    "concepts_tested": [],
    "answer": "D",
    "marks": 4
  },
  {
    "id": "JEE_Main_2015_iSzQWpXnIqltJoVX",
    "exam": "JEE Main",
    "year": 2015,
    "shift": "jee-main-2015-offline",
    "subject": "Mathematics",
    "topic": "Complex Numbers",
    "micro_topic": "Modulus Of Complex Numbers",
    "question_text": "A complex number z is said to be unimodular if $$\\,\\left| z \\right| = 1$$. Suppose $${z_1}$$ and $${z_2}$$ are complex numbers such that $${{{z_1} - 2{z_2}} \\over {2 - {z_1}\\overline {{z_2}} }}$$ is unimodular and $${z_2}$$ is not unimodular. Then the point $${z_1}$$ lies on a :",
    "question_type": "MCQ_single",
    "difficulty": 3,
    "concepts_tested": [],
    "answer": "A",
    "marks": 4
  },
  {
    "id": "JEE_Main_2015_l91h0jo8",
    "exam": "JEE Main",
    "year": 2015,
    "shift": "jee-main-2015-offline",
    "subject": "Mathematics",
    "topic": "Sets And Relations",
    "micro_topic": "Number Of Sets And Relations",
    "question_text": "Let A and B be two sets containing four and\ntwo elements respectively. Then, the number\nof subsets of the set A $\\times$ B , each having atleast\nthree elements are",
    "question_type": "MCQ_single",
    "difficulty": 3,
    "concepts_tested": [],
    "answer": "A",
    "marks": 4
  },
  {
    "id": "JEE_Main_2015_f1VCtY5QI3pxZNBP",
    "exam": "JEE Main",
    "year": 2015,
    "shift": "jee-main-2015-offline",
    "subject": "Physics",
    "topic": "Atoms And Nuclei",
    "micro_topic": "Bohrs Model And Hydrogen Spectrum",
    "question_text": "As an electron makes a transition from an excited state to the ground state of a hydrogen - like atom/ion :",
    "question_type": "MCQ_single",
    "difficulty": 3,
    "concepts_tested": [],
    "answer": "C",
    "marks": 4
  },
  {
    "id": "JEE_Main_2015_oGXPLiJTFE13Dh5Q",
    "exam": "JEE Main",
    "year": 2015,
    "shift": "jee-main-2015-offline",
    "subject": "Physics",
    "topic": "Electronic Devices",
    "micro_topic": "Semiconductor And P N Junction Diode",
    "question_text": "A red $$LED$$ emits light at $$0.1$$ watt uniformly around it. The amplitude of the electric field of the light at a distance of $$1$$ $$m$$ from the diode is :",
    "question_type": "MCQ_single",
    "difficulty": 3,
    "concepts_tested": [],
    "answer": "D",
    "marks": 4
  },
  {
    "id": "JEE_Main_2015_5nUCigmx53x8c8J4",
    "exam": "JEE Main",
    "year": 2015,
    "shift": "jee-main-2015-offline",
    "subject": "Physics",
    "topic": "Geometrical Optics",
    "micro_topic": "Refraction Tir And Prism",
    "question_text": "Monochromatic light is incident on a glass prism of angle $$A$$. If the refractive index of the material of the prism is $$\\mu $$, a ray, incident at an angle $$\\theta $$. on the face $$AB$$ would get transmitted through the face $$AC$$ of the prism provided :",
    "question_type": "MCQ_single",
    "difficulty": 3,
    "concepts_tested": [],
    "answer": "C",
    "marks": 4
  },
  {
    "id": "JEE_Main_2015_T88M1CToFCt9GBN2",
    "exam": "JEE Main",
    "year": 2015,
    "shift": "jee-main-2015-offline",
    "subject": "Physics",
    "topic": "Alternating Current",
    "micro_topic": "Growth And Decay Of Current",
    "question_text": "An $$LCR$$ circuit is equivalent to a damped pendulum. In an $$LCR$$ circuit the capacitor is charged to $${Q_0}$$ and then connected to the $$L$$ and $$R$$ as shown below : \n\nIf a student plots graphs of the square of maximum charge $$\\left( {Q_{Max}^2} \\right)$$ on the capacitor with time$$(t)$$ for two different values $${L_1}$$ and $${L_2}$$ $$\\left( {{L_1} > {L_2}} \\right)$$ of $$L$$ then which of the following represents this graph correctly ? \n$$\\left( {plots\\,\\,are\\,\\,schematic\\,\\,and\\,\\,niot\\,\\,drawn\\,\\,to\\,\\,scale} \\right)$$",
    "question_type": "MCQ_single",
    "difficulty": 3,
    "concepts_tested": [],
    "answer": "C",
    "marks": 4
  },
  {
    "id": "JEE_Main_2015_aDp4L5glGTvy8LIw",
    "exam": "JEE Main",
    "year": 2015,
    "shift": "jee-main-2015-offline",
    "subject": "Physics",
    "topic": "Alternating Current",
    "micro_topic": "Growth And Decay Of Current",
    "question_text": "An inductor $$(L=0.03$$ $$H)$$ and a resistor $$\\left( {R = 0.15\\,k\\Omega } \\right)$$ are connected in series to a battery of $$15V$$ $$EMF$$ in a circuit shown below. The key $${K_1}$$ has been kept closed for a long time. Then at $$t=0$$, $${K_1}$$ is opened and key $${K_2}$$  is closed simultaneously. At $$t=1$$ $$ms,$$ the current in the circuit will be : $$\\left( {{e^5} \\cong 150} \\right)$$",
    "question_type": "MCQ_single",
    "difficulty": 3,
    "concepts_tested": [],
    "answer": "B",
    "marks": 4
  },
  {
    "id": "JEE_Main_2015_zAAqcmyvG6YRPqcB",
    "exam": "JEE Main",
    "year": 2015,
    "shift": "jee-main-2015-offline",
    "subject": "Physics",
    "topic": "Wave Optics",
    "micro_topic": "Huygens Principle And Interference Of Light",
    "question_text": "On a hot summer night, the refractive index of air  is smallest near the ground and increases with height from  the ground. When a light beam is directed horizontally, the Huygens' principle leads us to conclude that as it travels, the light beam :",
    "question_type": "MCQ_single",
    "difficulty": 3,
    "concepts_tested": [],
    "answer": "B",
    "marks": 4
  },
  {
    "id": "JEE_Main_2015_irnszdUGj0LIsKov",
    "exam": "JEE Main",
    "year": 2015,
    "shift": "jee-main-2015-offline",
    "subject": "Physics",
    "topic": "Electromagnetic Induction",
    "micro_topic": "Inductance Self And Mutual",
    "question_text": "Two coaxial solenoids of different radius carry current $$I$$ in the same direction. $$\\overrightarrow {{F_1}} $$ be the magnetic force on the inner solenoid due to the outer one and $$\\overrightarrow {{F_2}} $$ be the magnetic force on the outer solenoid due to the inner one. Then :",
    "question_type": "MCQ_single",
    "difficulty": 3,
    "concepts_tested": [],
    "answer": "C",
    "marks": 4
  },
  {
    "id": "JEE_Main_2015_IxkapcQL8kDuPGeo",
    "exam": "JEE Main",
    "year": 2015,
    "shift": "jee-main-2015-offline",
    "subject": "Physics",
    "topic": "Wave Optics",
    "micro_topic": "Diffraction And Doppler Effect Of Light",
    "question_text": "Assuming human pupil to have a radius of $$0.25$$ $$cm$$ and a comfortable viewing distance of $$25$$ $$cm$$, the minimum separation between two objects that human eye can resolve at $$500$$ $$nm$$ wavelength is :",
    "question_type": "MCQ_single",
    "difficulty": 3,
    "concepts_tested": [],
    "answer": "D",
    "marks": 4
  },
  {
    "id": "JEE_Main_2015_o5riZKrbzx4V3Ck1",
    "exam": "JEE Main",
    "year": 2015,
    "shift": "jee-main-2015-offline",
    "subject": "Physics",
    "topic": "Magnetics",
    "micro_topic": "Force And Torque On Current Carrying Conductor",
    "question_text": "Two long current carrying thin wires, both with current $$I,$$ are held by insulating threads of length $$L$$ and are in equilibrium as shown in the figure, with threads making an angle $$'\\theta '$$ with the vertical. If wires have mass $$\\lambda $$ per unit-length then the value of $$I$$ is : \n($$g=$$ $$gravitational$$ $$acceleration$$ )",
    "question_type": "MCQ_single",
    "difficulty": 3,
    "concepts_tested": [],
    "answer": "D",
    "marks": 4
  },
  {
    "id": "JEE_Main_2015_m31XpxSsMEgpqHZR",
    "exam": "JEE Main",
    "year": 2015,
    "shift": "jee-main-2015-offline",
    "subject": "Physics",
    "topic": "Motion In A Straight Line",
    "micro_topic": "Relative Motion In One Dimension",
    "question_text": "Two stones are thrown up simultaneously from the edge of a cliff $$240$$ $$m$$ high with initial speed of $$10$$ $$m/s$$ and $$40$$ $$m/s$$ respectively. Which of the following graph best represents the time variation of relative position of the second stone with respect to the first ?\n(Assume stones do not rebound after hitting the ground and neglect air resistance, take $$g = 10m/{s^2}$$)\n(The figures are schematic and not drawn to scale)",
    "question_type": "MCQ_single",
    "difficulty": 3,
    "concepts_tested": [],
    "answer": "A",
    "marks": 4
  },
  {
    "id": "JEE_Main_2015_fYVSRq9Yd8YfaqJO",
    "exam": "JEE Main",
    "year": 2015,
    "shift": "jee-main-2015-offline",
    "subject": "Physics",
    "topic": "Current Electricity",
    "micro_topic": "Kirchhoffs Circuit Laws",
    "question_text": "In the circuit shown, the current in the $$1\\Omega $$ resistor is :",
    "question_type": "MCQ_single",
    "difficulty": 3,
    "concepts_tested": [],
    "answer": "A",
    "marks": 4
  },
  {
    "id": "JEE_Main_2015_gwzftriO0loiJL7b",
    "exam": "JEE Main",
    "year": 2015,
    "shift": "jee-main-2015-offline",
    "subject": "Physics",
    "topic": "Current Electricity",
    "micro_topic": "Ohms Law",
    "question_text": "When $$5V$$ potential difference is applied across a wire of length $$0.1$$ $$m,$$ the drift speed of electrons is $$2.5 \\times {10^{ - 4}}\\,\\,m{s^{ - 1}}.$$ If the electron density in the wire is $$8 \\times {10^{28}}\\,\\,{m^{ - 3}},$$ the resistivity of the material is close to :",
    "question_type": "MCQ_single",
    "difficulty": 3,
    "concepts_tested": [],
    "answer": "B",
    "marks": 4
  },
  {
    "id": "JEE_Main_2015_EyqEBAMhZ9COVcq4",
    "exam": "JEE Main",
    "year": 2015,
    "shift": "jee-main-2015-offline",
    "subject": "Physics",
    "topic": "Magnetics",
    "micro_topic": "Magnetic Moment",
    "question_text": "A rectangular loop of sides $$10$$ $$cm$$ and $$5$$ $$cm$$ carrying a current $$1$$ of $$12A$$ is placed in different orientations as shown in the figures below :\n\nIf there is a uniform magnetic field of $$0.3$$ $$T$$ in the positive $$z$$ direction, in which orientations the loop would be in $$(i)$$ stable equilibrium and $$(ii)$$ unstable equilibrium ?",
    "question_type": "MCQ_single",
    "difficulty": 3,
    "concepts_tested": [],
    "answer": "A",
    "marks": 4
  },
  {
    "id": "JEE_Main_2015_c0bxKdhVGVrfsYLY",
    "exam": "JEE Main",
    "year": 2015,
    "shift": "jee-main-2015-offline",
    "subject": "Physics",
    "topic": "Simple Harmonic Motion",
    "micro_topic": "Some Systems Of Executing Shm",
    "question_text": "A pendulum made of a uniform wire of cross sectional area $$A$$ has time period $$T.$$ When an additional mass $$M$$ is added to its bob, the time period changes to $${T_{M.}}$$ If the Young's modulus of the material of the wire is $$Y$$ then $${1 \\over Y}$$ is equal to : \n($$g=$$ $$gravitational$$ $$acceleration$$)",
    "question_type": "MCQ_single",
    "difficulty": 3,
    "concepts_tested": [],
    "answer": "C",
    "marks": 4
  },
  {
    "id": "JEE_Main_2015_Lh0FdaHGDIWBQYlf",
    "exam": "JEE Main",
    "year": 2015,
    "shift": "jee-main-2015-offline",
    "subject": "Physics",
    "topic": "Electrostatics",
    "micro_topic": "Electric Potential Energy And Electric Potential",
    "question_text": "A uniformly charged solid sphere of radius $$R$$ has potential $${V_0}$$ (measured with respect to $$\\infty $$) on its surface. For this sphere the equipotential surfaces with potentials $${{3{V_0}} \\over 2},\\,{{5{V_0}} \\over 4},\\,{{3{V_0}} \\over 4}$$ and $${{{V_0}} \\over 4}$$ have radius $${R_1},\\,\\,{R_2},\\,\\,{R_3}$$ and $${R_4}$$ respectively. Then",
    "question_type": "MCQ_single",
    "difficulty": 3,
    "concepts_tested": [],
    "answer": "A,B",
    "marks": 4
  },
  {
    "id": "JEE_Main_2015_Hos8OlAcFoS8N6RW",
    "exam": "JEE Main",
    "year": 2015,
    "shift": "jee-main-2015-offline",
    "subject": "Physics",
    "topic": "Electrostatics",
    "micro_topic": "Electric Field And Electric Field Intensity",
    "question_text": "A long cylindrical shell carries positives surfaces change $$\\sigma $$ in the upper half and negative surface charge - $$\\sigma $$ in the lower half. The electric field lines around the cylinder will look like figure given in : \n(figures are schematic and not drawn to scale)",
    "question_type": "MCQ_single",
    "difficulty": 3,
    "concepts_tested": [],
    "answer": "C",
    "marks": 4
  },
  {
    "id": "JEE_Main_2015_joTsPVk49bxuHH0a",
    "exam": "JEE Main",
    "year": 2015,
    "shift": "jee-main-2015-offline",
    "subject": "Physics",
    "topic": "Simple Harmonic Motion",
    "micro_topic": "Some Systems Of Executing Shm",
    "question_text": "For a simple pendulum, a graph is plotted between its kinetic energy $$(KE)$$ and potential energy $$(PE)$$ against its displacement $$d.$$ Which one of the following represents these correctly?  \n$$(graphs$$ $$are$$ $$schematic$$ $$and$$ $$not$$ $$drawn$$ $$to$$ $$scale)$$",
    "question_type": "MCQ_single",
    "difficulty": 3,
    "concepts_tested": [],
    "answer": "D",
    "marks": 4
  },
  {
    "id": "JEE_Main_2015_mJFG2q42WCIz3vJH",
    "exam": "JEE Main",
    "year": 2015,
    "shift": "jee-main-2015-offline",
    "subject": "Physics",
    "topic": "Capacitor",
    "micro_topic": "Capacitor In Circuit",
    "question_text": "In the given circuit, charges $${Q_2}$$ on the $$2\\mu F$$ capacitor changes as $$C$$ is varied from $$1\\,\\mu F$$ to $$3\\mu F.$$ $${Q_2}$$ as a function of $$'C'$$ is given properly by: \n$$\\left( {figures\\,\\,are\\,\\,drawn\\,\\,schematically\\,\\,and\\,\\,are\\,\\,not\\,\\,to\\,\\,scale} \\right)$$",
    "question_type": "MCQ_single",
    "difficulty": 3,
    "concepts_tested": [],
    "answer": "D",
    "marks": 4
  },
  {
    "id": "JEE_Main_2015_qDsE9riSZq9oH9xq",
    "exam": "JEE Main",
    "year": 2015,
    "shift": "jee-main-2015-offline",
    "subject": "Physics",
    "topic": "Heat And Thermodynamics",
    "micro_topic": "Thermodynamics Process",
    "question_text": "Consider a spherical shell of radius $$R$$ at temperature $$T$$. The black body radiation inside it can be considered as an ideal gas of photons with internal energy per unit volume $$u = {U \\over V}\\, \\propto \\,{T^4}$$ and pressure $$p = {1 \\over 3}\\left( {{U \\over V}} \\right)$$ . If the shell now undergoes an adiabatic expansion the relation between $$T$$ and $$R$$ is:",
    "question_type": "MCQ_single",
    "difficulty": 3,
    "concepts_tested": [],
    "answer": "A",
    "marks": 4
  },
  {
    "id": "JEE_Main_2015_ebq7jDvSzMjj78Vk",
    "exam": "JEE Main",
    "year": 2015,
    "shift": "jee-main-2015-offline",
    "subject": "Physics",
    "topic": "Heat And Thermodynamics",
    "micro_topic": "Heat Engine Second Law Of Thermodynamics And Carnot Engine",
    "question_text": "A solid body of constant heat capacity $$1$$ $$J/{}^ \\circ C$$ is being heated by keeping it in contact with reservoirs in two ways:\n$$(i)$$  Sequentially keeping in contact with $$2$$ reservoirs such that each reservoir \n$$\\,\\,\\,\\,\\,\\,\\,\\,$$supplies same amount of heat. \n$$(ii)$$ Sequentially keeping in contact with $$8$$ reservoirs such that each reservoir \n$$\\,\\,\\,\\,\\,\\,\\,\\,\\,\\,$$supplies same amount of heat. \nIn both the cases body is brought from initial temperature $${100^ \\circ }C$$ to final temperature $${200^ \\circ }C$$. Entropy change of the body in the two cases respectively is :",
    "question_type": "MCQ_single",
    "difficulty": 3,
    "concepts_tested": [],
    "answer": "D",
    "marks": 4
  },
  {
    "id": "JEE_Main_2015_gH901l7W9tkB4quo",
    "exam": "JEE Main",
    "year": 2015,
    "shift": "jee-main-2015-offline",
    "subject": "Physics",
    "topic": "Gravitation",
    "micro_topic": "Gravitational Potential And Gravitational Potential Energy",
    "question_text": "From a solid sphere of mass $$M$$ and radius $$R,$$ a spherical portion of radius $$R/2$$ is removed, as shown in the figure. Taking gravitational potential $$V=0$$ at $$r = \\infty ,$$ the potential at the center of the cavity thus formed is: ($$G=gravitational $$ $$constant$$)",
    "question_type": "MCQ_single",
    "difficulty": 3,
    "concepts_tested": [],
    "answer": "D",
    "marks": 4
  },
  {
    "id": "JEE_Main_2015_vkKkodUJbwcBvU05",
    "exam": "JEE Main",
    "year": 2015,
    "shift": "jee-main-2015-offline",
    "subject": "Physics",
    "topic": "Heat And Thermodynamics",
    "micro_topic": "Kinetic Theory Of Gases And Gas Laws",
    "question_text": "Consider an ideal gas confined in an isolated closed chamber. As the gas undergoes an adiabatic expansion, the average time of collision between molecules increases as $${V^q},$$ where $$V$$ is the volume of the gas. The value of $$q$$ is: $$\\left( {\\gamma  = {{{C_p}} \\over {{C_v}}}} \\right)$$",
    "question_type": "MCQ_single",
    "difficulty": 3,
    "concepts_tested": [],
    "answer": "A",
    "marks": 4
  },
  {
    "id": "JEE_Main_2015_zAeid4s9T1Uzjbdo",
    "exam": "JEE Main",
    "year": 2015,
    "shift": "jee-main-2015-offline",
    "subject": "Physics",
    "topic": "Center Of Mass",
    "micro_topic": "Collision",
    "question_text": "A particle of mass $$m$$ moving in the $$x$$ direction with speed $$2v$$ is hit by another particle of mass $$2m$$  moving in the $$y$$ direction with speed $$v.$$  If the collision is perfectly inelastic, the percentage loss in the energy during the collision is close to:",
    "question_type": "MCQ_single",
    "difficulty": 3,
    "concepts_tested": [],
    "answer": "A",
    "marks": 4
  },
  {
    "id": "JEE_Main_2015_a6lKQHUSUq7mYL0t",
    "exam": "JEE Main",
    "year": 2015,
    "shift": "jee-main-2015-offline",
    "subject": "Physics",
    "topic": "Rotational Motion",
    "micro_topic": "Moment Of Inertia",
    "question_text": "From a solid sphere of mass $$M$$ and radius $$R$$ a cube of maximum possible volume is cut. Moment of inertia of cube about an axis passing through its center and perpendicular to one of its face is:",
    "question_type": "MCQ_single",
    "difficulty": 3,
    "concepts_tested": [],
    "answer": "A",
    "marks": 4
  },
  {
    "id": "JEE_Main_2015_PnlIt96Qke6WKAUq",
    "exam": "JEE Main",
    "year": 2015,
    "shift": "jee-main-2015-offline",
    "subject": "Physics",
    "topic": "Laws Of Motion",
    "micro_topic": "Friction Force",
    "question_text": "Given in the figure are two blocks $$A$$ and $$B$$ of weight 20 N and 100 N, respectively. These are being pressed against a wall by a force $$F$$ as shown. If the coefficient of friction between the blocks is 0.1 and between block $$B$$ and the wall is 0.15, the frictional force applied by the wall on block $$B$$ is :",
    "question_type": "MCQ_single",
    "difficulty": 3,
    "concepts_tested": [],
    "answer": "A",
    "marks": 4
  },
  {
    "id": "JEE_Main_2015_xgq9perk5vcVZ7Xu",
    "exam": "JEE Main",
    "year": 2015,
    "shift": "jee-main-2015-offline",
    "subject": "Physics",
    "topic": "Center Of Mass",
    "micro_topic": "Center Of Mass Of Continuous Mass Distribution",
    "question_text": "Distance of the center of mass of a solid uniform cone from its vertex is $$z{}_0$$. If the radius of its base is $$R$$ and its height is $$h$$ then $$z{}_0$$ is equal to :",
    "question_type": "MCQ_single",
    "difficulty": 3,
    "concepts_tested": [],
    "answer": "D",
    "marks": 4
  },
  {
    "id": "JEE_Main_2015_0biZwoHVNUIxBTRk",
    "exam": "JEE Main",
    "year": 2015,
    "shift": "jee-main-2015-offline",
    "subject": "Physics",
    "topic": "Simple Harmonic Motion",
    "micro_topic": "Some Systems Of Executing Shm",
    "question_text": "The period of oscillation of a simple pendulum is $$T = 2\\pi \\sqrt {{L \\over g}} $$.  Measured value of L is 20.0 cm known to 1 mm accuracy and time for 100 oscillations of the pendulum is found to be 90 s using wrist watch of 1 s resolution. The accuracy in the determination of g is:",
    "question_type": "MCQ_single",
    "difficulty": 3,
    "concepts_tested": [],
    "answer": "D",
    "marks": 4
  }
]